<?xml version='1.0' encoding='utf-8'?>
<verb default="carbólaigh" disambig="">
  <verbalNoun default="carbólú" />
  <verbalAdjective default="carbólaithe" />
  <tenseForm default="carbólaigh" tense="Past" dependency="Indep" person="Base" />
  <tenseForm default="carbólaíomar" tense="Past" dependency="Indep" person="Pl1" />
  <tenseForm default="carbólaíodar" tense="Past" dependency="Indep" person="Pl3" />
  <tenseForm default="carbólaíodh" tense="Past" dependency="Indep" person="Auto" />
  <tenseForm default="carbólaigh" tense="Past" dependency="Dep" person="Base" />
  <tenseForm default="carbólaíomar" tense="Past" dependency="Dep" person="Pl1" />
  <tenseForm default="carbólaíodar" tense="Past" dependency="Dep" person="Pl3" />
  <tenseForm default="carbólaíodh" tense="Past" dependency="Dep" person="Auto" />
  <tenseForm default="carbólaíodh" tense="PastCont" dependency="Indep" person="Base" />
  <tenseForm default="carbólaínn" tense="PastCont" dependency="Indep" person="Sg1" />
  <tenseForm default="carbólaíteá" tense="PastCont" dependency="Indep" person="Sg2" />
  <tenseForm default="carbólaímis" tense="PastCont" dependency="Indep" person="Pl1" />
  <tenseForm default="carbólaídís" tense="PastCont" dependency="Indep" person="Pl3" />
  <tenseForm default="carbólaítí" tense="PastCont" dependency="Indep" person="Auto" />
  <tenseForm default="carbólaíodh" tense="PastCont" dependency="Dep" person="Base" />
  <tenseForm default="carbólaínn" tense="PastCont" dependency="Dep" person="Sg1" />
  <tenseForm default="carbólaíteá" tense="PastCont" dependency="Dep" person="Sg2" />
  <tenseForm default="carbólaímis" tense="PastCont" dependency="Dep" person="Pl1" />
  <tenseForm default="carbólaídís" tense="PastCont" dependency="Dep" person="Pl3" />
  <tenseForm default="carbólaítí" tense="PastCont" dependency="Dep" person="Auto" />
  <tenseForm default="carbólaíonn" tense="PresCont" dependency="Indep" person="Base" />
  <tenseForm default="carbólaím" tense="PresCont" dependency="Indep" person="Sg1" />
  <tenseForm default="carbólaímid" tense="PresCont" dependency="Indep" person="Pl1" />
  <tenseForm default="carbólaítear" tense="PresCont" dependency="Indep" person="Auto" />
  <tenseForm default="carbólaíonn" tense="PresCont" dependency="Dep" person="Base" />
  <tenseForm default="carbólaím" tense="PresCont" dependency="Dep" person="Sg1" />
  <tenseForm default="carbólaímid" tense="PresCont" dependency="Dep" person="Pl1" />
  <tenseForm default="carbólaítear" tense="PresCont" dependency="Dep" person="Auto" />
  <tenseForm default="carbólóidh" tense="Fut" dependency="Indep" person="Base" />
  <tenseForm default="carbólóimid" tense="Fut" dependency="Indep" person="Pl1" />
  <tenseForm default="carbólófar" tense="Fut" dependency="Indep" person="Auto" />
  <tenseForm default="carbólóidh" tense="Fut" dependency="Dep" person="Base" />
  <tenseForm default="carbólóimid" tense="Fut" dependency="Dep" person="Pl1" />
  <tenseForm default="carbólófar" tense="Fut" dependency="Dep" person="Auto" />
  <tenseForm default="carbólódh" tense="Cond" dependency="Indep" person="Base" />
  <tenseForm default="carbólóinn" tense="Cond" dependency="Indep" person="Sg1" />
  <tenseForm default="carbólófá" tense="Cond" dependency="Indep" person="Sg2" />
  <tenseForm default="carbólóimis" tense="Cond" dependency="Indep" person="Pl1" />
  <tenseForm default="carbólóidís" tense="Cond" dependency="Indep" person="Pl3" />
  <tenseForm default="carbólófaí" tense="Cond" dependency="Indep" person="Auto" />
  <tenseForm default="carbólódh" tense="Cond" dependency="Dep" person="Base" />
  <tenseForm default="carbólóinn" tense="Cond" dependency="Dep" person="Sg1" />
  <tenseForm default="carbólófá" tense="Cond" dependency="Dep" person="Sg2" />
  <tenseForm default="carbólóimis" tense="Cond" dependency="Dep" person="Pl1" />
  <tenseForm default="carbólóidís" tense="Cond" dependency="Dep" person="Pl3" />
  <tenseForm default="carbólófaí" tense="Cond" dependency="Dep" person="Auto" />
  <moodForm default="carbólaíodh" mood="Imper" person="Base" />
  <moodForm default="carbólaím" mood="Imper" person="Sg1" />
  <moodForm default="carbólaigh" mood="Imper" person="Sg2" />
  <moodForm default="carbólaímis" mood="Imper" person="Pl1" />
  <moodForm default="carbólaígí" mood="Imper" person="Pl2" />
  <moodForm default="carbólaídís" mood="Imper" person="Pl3" />
  <moodForm default="carbólaítear" mood="Imper" person="Auto" />
  <moodForm default="carbólaí" mood="Subj" person="Base" />
  <moodForm default="carbólaímid" mood="Subj" person="Pl1" />
  <moodForm default="carbólaítear" mood="Subj" person="Auto" />
</verb>
