<?xml version='1.0' encoding='utf-8'?>
<verb default="durdáil" disambig="">
  <verbalNoun default="durdáil" />
  <verbalAdjective default="durdáilte" />
  <tenseForm default="durdáil" tense="Past" dependency="Indep" person="Base" />
  <tenseForm default="durdálamar" tense="Past" dependency="Indep" person="Pl1" />
  <tenseForm default="durdáladar" tense="Past" dependency="Indep" person="Pl3" />
  <tenseForm default="durdáladh" tense="Past" dependency="Indep" person="Auto" />
  <tenseForm default="durdáil" tense="Past" dependency="Dep" person="Base" />
  <tenseForm default="durdálamar" tense="Past" dependency="Dep" person="Pl1" />
  <tenseForm default="durdáladar" tense="Past" dependency="Dep" person="Pl3" />
  <tenseForm default="durdáladh" tense="Past" dependency="Dep" person="Auto" />
  <tenseForm default="durdáladh" tense="PastCont" dependency="Indep" person="Base" />
  <tenseForm default="durdálainn" tense="PastCont" dependency="Indep" person="Sg1" />
  <tenseForm default="durdáilteá" tense="PastCont" dependency="Indep" person="Sg2" />
  <tenseForm default="durdálaimis" tense="PastCont" dependency="Indep" person="Pl1" />
  <tenseForm default="durdálaidís" tense="PastCont" dependency="Indep" person="Pl3" />
  <tenseForm default="durdáiltí" tense="PastCont" dependency="Indep" person="Auto" />
  <tenseForm default="durdáladh" tense="PastCont" dependency="Dep" person="Base" />
  <tenseForm default="durdálainn" tense="PastCont" dependency="Dep" person="Sg1" />
  <tenseForm default="durdáilteá" tense="PastCont" dependency="Dep" person="Sg2" />
  <tenseForm default="durdálaimis" tense="PastCont" dependency="Dep" person="Pl1" />
  <tenseForm default="durdálaidís" tense="PastCont" dependency="Dep" person="Pl3" />
  <tenseForm default="durdáiltí" tense="PastCont" dependency="Dep" person="Auto" />
  <tenseForm default="durdálann" tense="PresCont" dependency="Indep" person="Base" />
  <tenseForm default="durdálaim" tense="PresCont" dependency="Indep" person="Sg1" />
  <tenseForm default="durdálaimid" tense="PresCont" dependency="Indep" person="Pl1" />
  <tenseForm default="durdáiltear" tense="PresCont" dependency="Indep" person="Auto" />
  <tenseForm default="durdálann" tense="PresCont" dependency="Dep" person="Base" />
  <tenseForm default="durdálaim" tense="PresCont" dependency="Dep" person="Sg1" />
  <tenseForm default="durdálaimid" tense="PresCont" dependency="Dep" person="Pl1" />
  <tenseForm default="durdáiltear" tense="PresCont" dependency="Dep" person="Auto" />
  <tenseForm default="durdálfaidh" tense="Fut" dependency="Indep" person="Base" />
  <tenseForm default="durdálfaimid" tense="Fut" dependency="Indep" person="Pl1" />
  <tenseForm default="durdálfar" tense="Fut" dependency="Indep" person="Auto" />
  <tenseForm default="durdálfaidh" tense="Fut" dependency="Dep" person="Base" />
  <tenseForm default="durdálfaimid" tense="Fut" dependency="Dep" person="Pl1" />
  <tenseForm default="durdálfar" tense="Fut" dependency="Dep" person="Auto" />
  <tenseForm default="durdálfadh" tense="Cond" dependency="Indep" person="Base" />
  <tenseForm default="durdálfainn" tense="Cond" dependency="Indep" person="Sg1" />
  <tenseForm default="durdálfá" tense="Cond" dependency="Indep" person="Sg2" />
  <tenseForm default="durdálfaimis" tense="Cond" dependency="Indep" person="Pl1" />
  <tenseForm default="durdálfaidís" tense="Cond" dependency="Indep" person="Pl3" />
  <tenseForm default="durdálfaí" tense="Cond" dependency="Indep" person="Auto" />
  <tenseForm default="durdálfadh" tense="Cond" dependency="Dep" person="Base" />
  <tenseForm default="durdálfainn" tense="Cond" dependency="Dep" person="Sg1" />
  <tenseForm default="durdálfá" tense="Cond" dependency="Dep" person="Sg2" />
  <tenseForm default="durdálfaimis" tense="Cond" dependency="Dep" person="Pl1" />
  <tenseForm default="durdálfaidís" tense="Cond" dependency="Dep" person="Pl3" />
  <tenseForm default="durdálfaí" tense="Cond" dependency="Dep" person="Auto" />
  <moodForm default="durdáladh" mood="Imper" person="Base" />
  <moodForm default="durdálaim" mood="Imper" person="Sg1" />
  <moodForm default="durdáil" mood="Imper" person="Sg2" />
  <moodForm default="durdálaimis" mood="Imper" person="Pl1" />
  <moodForm default="durdálaigí" mood="Imper" person="Pl2" />
  <moodForm default="durdálaidís" mood="Imper" person="Pl3" />
  <moodForm default="durdáiltear" mood="Imper" person="Auto" />
  <moodForm default="durdála" mood="Subj" person="Base" />
  <moodForm default="durdálaimid" mood="Subj" person="Pl1" />
  <moodForm default="durdáiltear" mood="Subj" person="Auto" />
</verb>
