<?xml version='1.0' encoding='utf-8'?>
<verb default="séamáil" disambig="">
  <verbalNoun default="séamáil" />
  <verbalAdjective default="séamáilte" />
  <tenseForm default="séamáil" tense="Past" dependency="Indep" person="Base" />
  <tenseForm default="séamálamar" tense="Past" dependency="Indep" person="Pl1" />
  <tenseForm default="séamáladar" tense="Past" dependency="Indep" person="Pl3" />
  <tenseForm default="séamáladh" tense="Past" dependency="Indep" person="Auto" />
  <tenseForm default="séamáil" tense="Past" dependency="Dep" person="Base" />
  <tenseForm default="séamálamar" tense="Past" dependency="Dep" person="Pl1" />
  <tenseForm default="séamáladar" tense="Past" dependency="Dep" person="Pl3" />
  <tenseForm default="séamáladh" tense="Past" dependency="Dep" person="Auto" />
  <tenseForm default="séamáladh" tense="PastCont" dependency="Indep" person="Base" />
  <tenseForm default="séamálainn" tense="PastCont" dependency="Indep" person="Sg1" />
  <tenseForm default="séamáilteá" tense="PastCont" dependency="Indep" person="Sg2" />
  <tenseForm default="séamálaimis" tense="PastCont" dependency="Indep" person="Pl1" />
  <tenseForm default="séamálaidís" tense="PastCont" dependency="Indep" person="Pl3" />
  <tenseForm default="séamáiltí" tense="PastCont" dependency="Indep" person="Auto" />
  <tenseForm default="séamáladh" tense="PastCont" dependency="Dep" person="Base" />
  <tenseForm default="séamálainn" tense="PastCont" dependency="Dep" person="Sg1" />
  <tenseForm default="séamáilteá" tense="PastCont" dependency="Dep" person="Sg2" />
  <tenseForm default="séamálaimis" tense="PastCont" dependency="Dep" person="Pl1" />
  <tenseForm default="séamálaidís" tense="PastCont" dependency="Dep" person="Pl3" />
  <tenseForm default="séamáiltí" tense="PastCont" dependency="Dep" person="Auto" />
  <tenseForm default="séamálann" tense="PresCont" dependency="Indep" person="Base" />
  <tenseForm default="séamálaim" tense="PresCont" dependency="Indep" person="Sg1" />
  <tenseForm default="séamálaimid" tense="PresCont" dependency="Indep" person="Pl1" />
  <tenseForm default="séamáiltear" tense="PresCont" dependency="Indep" person="Auto" />
  <tenseForm default="séamálann" tense="PresCont" dependency="Dep" person="Base" />
  <tenseForm default="séamálaim" tense="PresCont" dependency="Dep" person="Sg1" />
  <tenseForm default="séamálaimid" tense="PresCont" dependency="Dep" person="Pl1" />
  <tenseForm default="séamáiltear" tense="PresCont" dependency="Dep" person="Auto" />
  <tenseForm default="séamálfaidh" tense="Fut" dependency="Indep" person="Base" />
  <tenseForm default="séamálfaimid" tense="Fut" dependency="Indep" person="Pl1" />
  <tenseForm default="séamálfar" tense="Fut" dependency="Indep" person="Auto" />
  <tenseForm default="séamálfaidh" tense="Fut" dependency="Dep" person="Base" />
  <tenseForm default="séamálfaimid" tense="Fut" dependency="Dep" person="Pl1" />
  <tenseForm default="séamálfar" tense="Fut" dependency="Dep" person="Auto" />
  <tenseForm default="séamálfadh" tense="Cond" dependency="Indep" person="Base" />
  <tenseForm default="séamálfainn" tense="Cond" dependency="Indep" person="Sg1" />
  <tenseForm default="séamálfá" tense="Cond" dependency="Indep" person="Sg2" />
  <tenseForm default="séamálfaimis" tense="Cond" dependency="Indep" person="Pl1" />
  <tenseForm default="séamálfaidís" tense="Cond" dependency="Indep" person="Pl3" />
  <tenseForm default="séamálfaí" tense="Cond" dependency="Indep" person="Auto" />
  <tenseForm default="séamálfadh" tense="Cond" dependency="Dep" person="Base" />
  <tenseForm default="séamálfainn" tense="Cond" dependency="Dep" person="Sg1" />
  <tenseForm default="séamálfá" tense="Cond" dependency="Dep" person="Sg2" />
  <tenseForm default="séamálfaimis" tense="Cond" dependency="Dep" person="Pl1" />
  <tenseForm default="séamálfaidís" tense="Cond" dependency="Dep" person="Pl3" />
  <tenseForm default="séamálfaí" tense="Cond" dependency="Dep" person="Auto" />
  <moodForm default="séamáladh" mood="Imper" person="Base" />
  <moodForm default="séamálaim" mood="Imper" person="Sg1" />
  <moodForm default="séamáil" mood="Imper" person="Sg2" />
  <moodForm default="séamálaimis" mood="Imper" person="Pl1" />
  <moodForm default="séamálaigí" mood="Imper" person="Pl2" />
  <moodForm default="séamálaidís" mood="Imper" person="Pl3" />
  <moodForm default="séamáiltear" mood="Imper" person="Auto" />
  <moodForm default="séamála" mood="Subj" person="Base" />
  <moodForm default="séamálaimid" mood="Subj" person="Pl1" />
  <moodForm default="séamáiltear" mood="Subj" person="Auto" />
</verb>
