<?xml version='1.0' encoding='utf-8'?>
<verb default="taiscéal" disambig="">
  <verbalNoun default="taiscéaladh" />
  <verbalAdjective default="taiscéalta" />
  <tenseForm default="taiscéal" tense="Past" dependency="Indep" person="Base" />
  <tenseForm default="taiscéalamar" tense="Past" dependency="Indep" person="Pl1" />
  <tenseForm default="taiscéaladar" tense="Past" dependency="Indep" person="Pl3" />
  <tenseForm default="taiscéaladh" tense="Past" dependency="Indep" person="Auto" />
  <tenseForm default="taiscéal" tense="Past" dependency="Dep" person="Base" />
  <tenseForm default="taiscéalamar" tense="Past" dependency="Dep" person="Pl1" />
  <tenseForm default="taiscéaladar" tense="Past" dependency="Dep" person="Pl3" />
  <tenseForm default="taiscéaladh" tense="Past" dependency="Dep" person="Auto" />
  <tenseForm default="taiscéaladh" tense="PastCont" dependency="Indep" person="Base" />
  <tenseForm default="taiscéalainn" tense="PastCont" dependency="Indep" person="Sg1" />
  <tenseForm default="taiscéaltá" tense="PastCont" dependency="Indep" person="Sg2" />
  <tenseForm default="taiscéalaimis" tense="PastCont" dependency="Indep" person="Pl1" />
  <tenseForm default="taiscéalaidís" tense="PastCont" dependency="Indep" person="Pl3" />
  <tenseForm default="taiscéaltaí" tense="PastCont" dependency="Indep" person="Auto" />
  <tenseForm default="taiscéaladh" tense="PastCont" dependency="Dep" person="Base" />
  <tenseForm default="taiscéalainn" tense="PastCont" dependency="Dep" person="Sg1" />
  <tenseForm default="taiscéaltá" tense="PastCont" dependency="Dep" person="Sg2" />
  <tenseForm default="taiscéalaimis" tense="PastCont" dependency="Dep" person="Pl1" />
  <tenseForm default="taiscéalaidís" tense="PastCont" dependency="Dep" person="Pl3" />
  <tenseForm default="taiscéaltaí" tense="PastCont" dependency="Dep" person="Auto" />
  <tenseForm default="taiscéalann" tense="PresCont" dependency="Indep" person="Base" />
  <tenseForm default="taiscéalaim" tense="PresCont" dependency="Indep" person="Sg1" />
  <tenseForm default="taiscéalaimid" tense="PresCont" dependency="Indep" person="Pl1" />
  <tenseForm default="taiscéaltar" tense="PresCont" dependency="Indep" person="Auto" />
  <tenseForm default="taiscéalann" tense="PresCont" dependency="Dep" person="Base" />
  <tenseForm default="taiscéalaim" tense="PresCont" dependency="Dep" person="Sg1" />
  <tenseForm default="taiscéalaimid" tense="PresCont" dependency="Dep" person="Pl1" />
  <tenseForm default="taiscéaltar" tense="PresCont" dependency="Dep" person="Auto" />
  <tenseForm default="taiscéalfaidh" tense="Fut" dependency="Indep" person="Base" />
  <tenseForm default="taiscéalfaimid" tense="Fut" dependency="Indep" person="Pl1" />
  <tenseForm default="taiscéalfar" tense="Fut" dependency="Indep" person="Auto" />
  <tenseForm default="taiscéalfaidh" tense="Fut" dependency="Dep" person="Base" />
  <tenseForm default="taiscéalfaimid" tense="Fut" dependency="Dep" person="Pl1" />
  <tenseForm default="taiscéalfar" tense="Fut" dependency="Dep" person="Auto" />
  <tenseForm default="taiscéalfadh" tense="Cond" dependency="Indep" person="Base" />
  <tenseForm default="taiscéalfainn" tense="Cond" dependency="Indep" person="Sg1" />
  <tenseForm default="taiscéalfá" tense="Cond" dependency="Indep" person="Sg2" />
  <tenseForm default="taiscéalfaimis" tense="Cond" dependency="Indep" person="Pl1" />
  <tenseForm default="taiscéalfaidís" tense="Cond" dependency="Indep" person="Pl3" />
  <tenseForm default="taiscéalfaí" tense="Cond" dependency="Indep" person="Auto" />
  <tenseForm default="taiscéalfadh" tense="Cond" dependency="Dep" person="Base" />
  <tenseForm default="taiscéalfainn" tense="Cond" dependency="Dep" person="Sg1" />
  <tenseForm default="taiscéalfá" tense="Cond" dependency="Dep" person="Sg2" />
  <tenseForm default="taiscéalfaimis" tense="Cond" dependency="Dep" person="Pl1" />
  <tenseForm default="taiscéalfaidís" tense="Cond" dependency="Dep" person="Pl3" />
  <tenseForm default="taiscéalfaí" tense="Cond" dependency="Dep" person="Auto" />
  <moodForm default="taiscéaladh" mood="Imper" person="Base" />
  <moodForm default="taiscéalaim" mood="Imper" person="Sg1" />
  <moodForm default="taiscéal" mood="Imper" person="Sg2" />
  <moodForm default="taiscéalaimis" mood="Imper" person="Pl1" />
  <moodForm default="taiscéalaigí" mood="Imper" person="Pl2" />
  <moodForm default="taiscéalaidís" mood="Imper" person="Pl3" />
  <moodForm default="taiscéaltar" mood="Imper" person="Auto" />
  <moodForm default="taiscéala" mood="Subj" person="Base" />
  <moodForm default="taiscéalaimid" mood="Subj" person="Pl1" />
  <moodForm default="taiscéaltar" mood="Subj" person="Auto" />
</verb>
